persistent_data_structures/__init__.py
persistent_data_structures/base_persistent.py
persistent_data_structures/persistent_array.py
persistent_data_structures/persistent_list.py
persistent_data_structures/persistent_map.py
persistent_data_structures-0.3.0.dist-info/METADATA
persistent_data_structures-0.3.0.dist-info/WHEEL
persistent_data_structures-0.3.0.dist-info/RECORD
