Metadata-Version: 2.1
Name: persistent-data-structures
Version: 0.3.0
Summary: 
Author: Your Name
Author-email: you@example.com
Requires-Python: >=3.10,<4.0
Classifier: Programming Language :: Python :: 3
Classifier: Programming Language :: Python :: 3.10
Classifier: Programming Language :: Python :: 3.11
Classifier: Programming Language :: Python :: 3.12
Classifier: Programming Language :: Python :: 3.13
Requires-Dist: numpy (>=2.1.3,<3.0.0)
Requires-Dist: pytest (>=8.3.3,<9.0.0)
